{"cameraMode":{"drawMode":0,"name":"Shaded","section":"Shading Mode"},"sceneLighting":false,"audioPlay":false,"sceneViewState":{"m_AlwaysRefresh":false,"showFog":true,"showSkybox":false,"showFlares":true,"showImageEffects":true,"showParticleSystems":true,"showVisualEffectGraphs":true,"m_FxEnabled":true},"in2DMode":false,"pivot":{"x":0.0,"y":1.877466082572937,"z":0.18397381901741029},"rotation":{"x":0.0325775183737278,"y":0.9398218393325806,"z":-0.09364160895347595,"w":0.3269624412059784},"size":1.8333683013916016,"orthographic":false}